splinebasis/__init__.py
splinebasis/_version.py
splinebasis/ispline.py
splinebasis/mspline.py
spline_basis-0.1.dist-info/LICENSE
spline_basis-0.1.dist-info/METADATA
spline_basis-0.1.dist-info/WHEEL
spline_basis-0.1.dist-info/top_level.txt
spline_basis-0.1.dist-info/RECORD
